epita_coding_style/.clang-format
epita_coding_style/__init__.py
epita_coding_style/checker.py
epita_coding_style/checks.py
epita_coding_style/config.py
epita_coding_style/core.py
epita_coding_style-2.4.1.dist-info/METADATA
epita_coding_style-2.4.1.dist-info/WHEEL
epita_coding_style-2.4.1.dist-info/entry_points.txt
epita_coding_style-2.4.1.dist-info/RECORD
