Metadata-Version: 2.4
Name: epita-coding-style
Version: 2.4.1
Summary: EPITA C Coding Style Checker - validates C code against EPITA coding standards
Project-URL: Homepage, https://github.com/KazeTachinuu/coding-style
Project-URL: Repository, https://github.com/KazeTachinuu/coding-style
Project-URL: Issues, https://github.com/KazeTachinuu/coding-style/issues
Author: Hugo
License-Expression: MIT
Keywords: c,checker,coding-style,epita,linter
Classifier: Development Status :: 5 - Production/Stable
Classifier: Environment :: Console
Classifier: Intended Audience :: Developers
Classifier: Intended Audience :: Education
Classifier: License :: OSI Approved :: MIT License
Classifier: Operating System :: OS Independent
Classifier: Programming Language :: C
Classifier: Programming Language :: Python :: 3
Classifier: Programming Language :: Python :: 3.10
Classifier: Programming Language :: Python :: 3.11
Classifier: Programming Language :: Python :: 3.12
Classifier: Topic :: Software Development :: Quality Assurance
Requires-Python: >=3.10
Requires-Dist: tomli>=2.0.0; python_version < '3.11'
Requires-Dist: tree-sitter-c>=0.23.0
Requires-Dist: tree-sitter>=0.23.0
Provides-Extra: dev
Requires-Dist: pytest>=8.0.0; extra == 'dev'
